augmentationer/__init__.py
augmentationer/augmentationer.py
augmentationer/function.py
augmentationer/visualizer.py
augmentationer-0.4.2.dist-info/LICENSE
augmentationer-0.4.2.dist-info/METADATA
augmentationer-0.4.2.dist-info/WHEEL
augmentationer-0.4.2.dist-info/RECORD
